.gitignore
.python-version
PKG-INFO
README.md
agent.py
pyproject.toml
uv.lock
cli_chatbot-0.1.4.dist-info/METADATA
cli_chatbot-0.1.4.dist-info/WHEEL
cli_chatbot-0.1.4.dist-info/RECORD
