Metadata-Version: 2.4
Name: cli-chatbot
Version: 0.1.4
Summary: Add your description here
Requires-Python: >=3.12
Requires-Dist: build>=1.3.0
Requires-Dist: fastmcp>=2.11.3
Requires-Dist: litellm>=1.75.9
Requires-Dist: rich>=14.1.0
Requires-Dist: twine>=6.1.0
